mem0/__init__.py
mem0/client/__init__.py
mem0/client/main.py
mem0/memory/__init__.py
mem0/memory/setup.py
mem0/memory/telemetry.py
memzero-0.0.6.dist-info/METADATA
memzero-0.0.6.dist-info/WHEEL
memzero-0.0.6.dist-info/RECORD
