Metadata-Version: 2.1
Name: memzero
Version: 0.0.6
Summary: Long-term memory for AI Agents
Home-page: https://docs.mem0.ai
License: Apache-2.0
Author: Deshraj Yadav
Author-email: deshraj@mem0.ai
Requires-Python: >=3.9,<4.0
Classifier: License :: OSI Approved :: Apache Software License
Classifier: Programming Language :: Python :: 3
Classifier: Programming Language :: Python :: 3.9
Classifier: Programming Language :: Python :: 3.10
Classifier: Programming Language :: Python :: 3.11
Requires-Dist: httpx (>=0.27.0,<0.28.0)
Requires-Dist: posthog (>=3.5.0,<4.0.0)
Requires-Dist: pydantic (>=2.7.3,<3.0.0)
